main/__init__.py
main/data_processor/__init__.py
main/data_processor/configuration.py
main/data_processor/entity.py
main/data_processor/performanceAnalizer.py
main/data_transformer/__init__.py
main/data_transformer/abstract_parser.py
main/data_transformer/csv_parser.py
main/data_transformer/custom_exception.py
main/data_transformer/data_manager_factory.py
main/data_transformer/json_parser.py
main/data_transformer/xml_parser.py
PerformanceAnalyzerSystem-0.0.1.dist-info/LICENSE.txt
PerformanceAnalyzerSystem-0.0.1.dist-info/METADATA
PerformanceAnalyzerSystem-0.0.1.dist-info/WHEEL
PerformanceAnalyzerSystem-0.0.1.dist-info/top_level.txt
PerformanceAnalyzerSystem-0.0.1.dist-info/RECORD
