Metadata-Version: 2.1
Name: PerformanceAnalyzerSystem
Version: 0.0.1
Summary: This is a customization analysis system that supports multiple data formats (JSON, XML, CSV) and has the capability to be configured and used across multiple domains.
Author-email: Nayeli <naye.montiel.1806@gmail.com>, Karthiga <karthigaksk@gmail.com>
Project-URL: Homepage, https://github.com/Naye013/Data533-Step3-ContinuousIntergration
Project-URL: Issues, https://github.com/Naye013/Data533-Step3-ContinuousIntergration/issues
Classifier: Programming Language :: Python :: 3
Classifier: License :: OSI Approved :: MIT License
Classifier: Operating System :: OS Independent
Requires-Python: >=3.8
License-File: LICENSE.txt
